src/example_package_SolarisNeko/__init__.py
src/example_package_SolarisNeko/demo.py
demo_solarisneko-0.0.1.dist-info/METADATA
demo_solarisneko-0.0.1.dist-info/WHEEL
demo_solarisneko-0.0.1.dist-info/licenses/LICENSE
demo_solarisneko-0.0.1.dist-info/RECORD
