Metadata-Version: 2.1
Name: demo_solarisneko
Version: 0.0.1
Summary: try to upload to Pypi
Project-URL: Homepage, https://github.com/SolarisNeko/python-try-to-upload-pypi
Project-URL: Bug Tracker, https://github.com/SolarisNeko/python-try-to-upload-pypi/issues
Author-email: SolarisNeko <1417015340@qq.com>
License-File: LICENSE
Classifier: License :: OSI Approved :: MIT License
Classifier: Operating System :: OS Independent
Classifier: Programming Language :: Python :: 3
Requires-Python: >=3.7
